Ass 3 8B/R11617302.v

// Mason Marnell
// 32to1 Mux

/*
The videos are really helping me understand
(unless i did this wrong). Keep up the good work!
*/

module top(S,I,Y);

input [4:0] S;
input [31:0] I;
output Y;

mux32to1 U0(S,I,Y);


// Its good practice to only link
// other modules to "top" module.

endmodule

module mux32to1(S,I,Y);

input [31:0] I;
input [4:0] S;
output Y;

wire [31:0] W;

d5to32 u0(.A(S), .D(W));


//you could just do assign Y = W[31] & I[31] | W[30] & I[30] .....

assign Y = | (W & I); //more concise

endmodule


module d5to32(A, D);

input [4:0] A;
output [31:0] D;

wire [11:0] W;

//Module instantiations
d3to8 u0(.A(A[4:2]), .D(W[11:4]));
d2to4 u1(.A(A[1:0]), .D(W[3:0]));

//AND gates
assign D[31] = W[11] & W[3];
assign D[30] = W[11] & W[2];
assign D[29] = W[11] & W[1];
assign D[28] = W[11] & W[0];

assign D[27] = W[10] & W[3];
assign D[26] = W[10] & W[2];
assign D[25] = W[10] & W[1];
assign D[24] = W[10] & W[0];

assign D[23] = W[9] & W[3];
assign D[22] = W[9] & W[2];
assign D[21] = W[9] & W[1];
assign D[20] = W[9] & W[0];

assign D[19] = W[8] & W[3];
assign D[18] = W[8] & W[2];
assign D[17] = W[8] & W[1];
assign D[16] = W[8] & W[0];

assign D[15] = W[7] & W[3];
assign D[14] = W[7] & W[2];
assign D[13] = W[7] & W[1];
assign D[12] = W[7] & W[0];

assign D[11] = W[6] & W[3];
assign D[10] = W[6] & W[2];
assign D[9] = W[6] & W[1];
assign D[8] = W[6] & W[0];

assign D[7] = W[5] & W[3];
assign D[6] = W[5] & W[2];
assign D[5] = W[5] & W[1];
assign D[4] = W[5] & W[0];

assign D[3] = W[4] & W[3];
assign D[2] = W[4] & W[2];
assign D[1] = W[4] & W[1];
assign D[0] = W[4] & W[0];

endmodule


module d3to8(A, D);

input [2:0] A;
output [7:0] D;

wire [5:0] W;

//Module Instantiations
d2to4 u0(.A(A[2:1]),    .D(W[5:2]));
d1to2 u1(.A(A[0]),      .D(W[1:0]));

//AND gates
assign D[7] = W[5] & W[1];
assign D[6] = W[5] & W[0];
assign D[5] = W[4] & W[1];
assign D[4] = W[4] & W[0];
assign D[3] = W[3] & W[1];
assign D[2] = W[3] & W[0];
assign D[1] = W[2] & W[1];
assign D[0] = W[2] & W[0];

endmodule

module d2to4(A, D);

input [1:0] A;
output [3:0] D;

wire [3:0] W;

//Module Instantiations
d1to2 u0(.A(A[1]), .D(W[3:2]));
d1to2 u1(.A(A[0]), .D(W[1:0]));

//.__ is the lower level decoder
//...( is being assigned to different
//                  higher end indexes(?)


//AND gates
assign D[3] = W[3] & W[1];
assign D[2] = W[3] & W[0];
assign D[1] = W[2] & W[1];
assign D[0] = W[2] & W[0];

endmodule

module d1to2(A,D);

input A;
output [1:0] D;

assign D[1] = ~A;
assign D[0] = A;

endmodule

Ass 3 8B/testbench.v
`timescale 1 ns / 1ns
`include "R11617302.v"

module testbench;

reg [31:0] I;
reg [4:0] S;

wire Y;

top uut(S,I,Y);

initial begin
    $dumpfile("mux32to1.vcd");
    $dumpvars(0, testbench);


    I =  32'b01010101010101010101010101010101; #20;

    S = 5'd0;#20;
    S = 5'd1;#20;
    S = 5'd2;#20;
    S = 5'd3;#20;
    S = 5'd4;#20;
    S = 5'd5;#20;
    S = 5'd6;#20;
    S = 5'd7;#20;
    S = 5'd8;#20;
    S = 5'd9;#20;
    S = 5'd10;#20;
    S = 5'd11;#20;
    S = 5'd12;#20;
    S = 5'd13;#20;
    S = 5'd14;#20;
    S = 5'd15;#20;
    S = 5'd16;#20;
    S = 5'd17;#20;
    S = 5'd18;#20;
    S = 5'd19;#20;
    S = 5'd20;#20;
    S = 5'd21;#20;
    S = 5'd22;#20;
    S = 5'd23;#20;
    S = 5'd24;#20;
    S = 5'd25;#20;
    S = 5'd26;#20;
    S = 5'd27;#20;
    S = 5'd28;#20;
    S = 5'd29;#20;
    S = 5'd30;#20;
    S = 5'd31;#20;
    



    //the important thing is that we cycle through S
    //ie, load a value into I and exhaust S


end
endmodule

Ass 3 8B/mux32to1.vcd
$date
	Mon Apr 13 15:16:48 2020
$end
$version
	Icarus Verilog
$end
$timescale
	1ns
$end
$scope module testbench $end
$var wire 1 ! Y $end
$var reg 32 " I [31:0] $end
$var reg 5 # S [4:0] $end
$scope module uut $end
$var wire 32 $ I [31:0] $end
$var wire 5 % S [4:0] $end
$var wire 1 ! Y $end
$scope module U0 $end
$var wire 32 & I [31:0] $end
$var wire 5 ' S [4:0] $end
$var wire 1 ! Y $end
$var wire 32 ( W [31:0] $end
$scope module u0 $end
$var wire 5 ) A [4:0] $end
$var wire 12 * W [11:0] $end
$var wire 32 + D [31:0] $end
$scope module u0 $end
$var wire 3 , A [2:0] $end
$var wire 6 - W [5:0] $end
$var wire 8 . D [7:0] $end
$scope module u0 $end
$var wire 2 / A [1:0] $end
$var wire 4 0 W [3:0] $end
$var wire 4 1 D [3:0] $end
$scope module u0 $end
$var wire 1 2 A $end
$var wire 2 3 D [1:0] $end
$upscope $end
$scope module u1 $end
$var wire 1 4 A $end
$var wire 2 5 D [1:0] $end
$upscope $end
$upscope $end
$scope module u1 $end
$var wire 1 6 A $end
$var wire 2 7 D [1:0] $end
$upscope $end
$upscope $end
$scope module u1 $end
$var wire 2 8 A [1:0] $end
$var wire 4 9 W [3:0] $end
$var wire 4 : D [3:0] $end
$scope module u0 $end
$var wire 1 ; A $end
$var wire 2 < D [1:0] $end
$upscope $end
$scope module u1 $end
$var wire 1 = A $end
$var wire 2 > D [1:0] $end
$upscope $end
$upscope $end
$upscope $end
$upscope $end
$upscope $end
$upscope $end
$enddefinitions $end
#0
$dumpvars
bx >
x=
bx <
x;
bx :
bx 9
bx 8
bx 7
x6
bx 5
x4
bx 3
x2
bx 1
bx 0
bx /
bx .
bx -
bx ,
bx +
bx *
bx )
bx (
bx '
b1010101010101010101010101010101 &
bx %
b1010101010101010101010101010101 $
bx #
b1010101010101010101010101010101 "
x!
$end
#20
0!
b10000000000000000000000000000000 (
b10000000000000000000000000000000 +
b1000 1
b10000000 .
b100000001000 *
b1000 :
b10 3
02
b1010 0
b10 5
04
b0 /
b100010 -
b10 7
06
b10 <
0;
b1010 9
b10 >
0=
b0 ,
b0 8
b0 #
b0 %
b0 '
b0 )
#40
1!
b1000000000000000000000000000000 (
b1000000000000000000000000000000 +
b100000000100 *
b100 :
b1001 9
b1 >
1=
b1 8
b1 #
b1 %
b1 '
b1 )
#60
0!
b100000000000000000000000000000 (
b100000000000000000000000000000 +
b100000000010 *
b10 :
b1 <
1;
b110 9
b10 >
0=
b10 8
b10 #
b10 %
b10 '
b10 )
#80
1!
b10000000000000000000000000000 (
b10000000000000000000000000000 +
b100000000001 *
b1 :
b101 9
b1 >
1=
b11 8
b11 #
b11 %
b11 '
b11 )
#100
0!
b1000000000000000000000000000 (
b1000000000000000000000000000 +
b1000000 .
b10000001000 *
b1000 :
b100001 -
b1 7
16
b10 <
0;
b1010 9
b10 >
0=
b1 ,
b0 8
b100 #
b100 %
b100 '
b100 )
#120
1!
b100000000000000000000000000 (
b100000000000000000000000000 +
b10000000100 *
b100 :
b1001 9
b1 >
1=
b1 8
b101 #
b101 %
b101 '
b101 )
#140
0!
b10000000000000000000000000 (
b10000000000000000000000000 +
b10000000010 *
b10 :
b1 <
1;
b110 9
b10 >
0=
b10 8
b110 #
b110 %
b110 '
b110 )
#160
1!
b1000000000000000000000000 (
b1000000000000000000000000 +
b10000000001 *
b1 :
b101 9
b1 >
1=
b11 8
b111 #
b111 %
b111 '
b111 )
#180
0!
b100000000000000000000000 (
b100000000000000000000000 +
b100 1
b100000 .
b1000001000 *
b1000 :
b1001 0
b1 5
14
b1 /
b10010 -
b10 7
06
b10 <
0;
b1010 9
b10 >
0=
b10 ,
b0 8
b1000 #
b1000 %
b1000 '
b1000 )
#200
1!
b10000000000000000000000 (
b10000000000000000000000 +
b1000000100 *
b100 :
b1001 9
b1 >
1=
b1 8
b1001 #
b1001 %
b1001 '
b1001 )
#220
0!
b1000000000000000000000 (
b1000000000000000000000 +
b1000000010 *
b10 :
b1 <
1;
b110 9
b10 >
0=
b10 8
b1010 #
b1010 %
b1010 '
b1010 )
#240
1!
b100000000000000000000 (
b100000000000000000000 +
b1000000001 *
b1 :
b101 9
b1 >
1=
b11 8
b1011 #
b1011 %
b1011 '
b1011 )
#260
0!
b10000000000000000000 (
b10000000000000000000 +
b10000 .
b100001000 *
b1000 :
b10001 -
b1 7
16
b10 <
0;
b1010 9
b10 >
0=
b11 ,
b0 8
b1100 #
b1100 %
b1100 '
b1100 )
#280
1!
b1000000000000000000 (
b1000000000000000000 +
b100000100 *
b100 :
b1001 9
b1 >
1=
b1 8
b1101 #
b1101 %
b1101 '
b1101 )
#300
0!
b100000000000000000 (
b100000000000000000 +
b100000010 *
b10 :
b1 <
1;
b110 9
b10 >
0=
b10 8
b1110 #
b1110 %
b1110 '
b1110 )
#320
1!
b10000000000000000 (
b10000000000000000 +
b100000001 *
b1 :
b101 9
b1 >
1=
b11 8
b1111 #
b1111 %
b1111 '
b1111 )
#340
0!
b1000000000000000 (
b1000000000000000 +
b10 1
b1000 .
b10001000 *
b1000 :
b1 3
12
b110 0
b10 5
04
b10 /
b1010 -
b10 7
06
b10 <
0;
b1010 9
b10 >
0=
b100 ,
b0 8
b10000 #
b10000 %
b10000 '
b10000 )
#360
1!
b100000000000000 (
b100000000000000 +
b10000100 *
b100 :
b1001 9
b1 >
1=
b1 8
b10001 #
b10001 %
b10001 '
b10001 )
#380
0!
b10000000000000 (
b10000000000000 +
b10000010 *
b10 :
b1 <
1;
b110 9
b10 >
0=
b10 8
b10010 #
b10010 %
b10010 '
b10010 )
#400
1!
b1000000000000 (
b1000000000000 +
b10000001 *
b1 :
b101 9
b1 >
1=
b11 8
b10011 #
b10011 %
b10011 '
b10011 )
#420
0!
b100000000000 (
b100000000000 +
b100 .
b1001000 *
b1000 :
b1001 -
b1 7
16
b10 <
0;
b1010 9
b10 >
0=
b101 ,
b0 8
b10100 #
b10100 %
b10100 '
b10100 )
#440
1!
b10000000000 (
b10000000000 +
b1000100 *
b100 :
b1001 9
b1 >
1=
b1 8
b10101 #
b10101 %
b10101 '
b10101 )
#460
0!
b1000000000 (
b1000000000 +
b1000010 *
b10 :
b1 <
1;
b110 9
b10 >
0=
b10 8
b10110 #
b10110 %
b10110 '
b10110 )
#480
1!
b100000000 (
b100000000 +
b1000001 *
b1 :
b101 9
b1 >
1=
b11 8
b10111 #
b10111 %
b10111 '
b10111 )
#500
0!
b10000000 (
b10000000 +
b1 1
b10 .
b101000 *
b1000 :
b101 0
b1 5
14
b11 /
b110 -
b10 7
06
b10 <
0;
b1010 9
b10 >
0=
b110 ,
b0 8
b11000 #
b11000 %
b11000 '
b11000 )
#520
1!
b1000000 (
b1000000 +
b100100 *
b100 :
b1001 9
b1 >
1=
b1 8
b11001 #
b11001 %
b11001 '
b11001 )
#540
0!
b100000 (
b100000 +
b100010 *
b10 :
b1 <
1;
b110 9
b10 >
0=
b10 8
b11010 #
b11010 %
b11010 '
b11010 )
#560
1!
b10000 (
b10000 +
b100001 *
b1 :
b101 9
b1 >
1=
b11 8
b11011 #
b11011 %
b11011 '
b11011 )
#580
0!
b1000 (
b1000 +
b1 .
b11000 *
b1000 :
b101 -
b1 7
16
b10 <
0;
b1010 9
b10 >
0=
b111 ,
b0 8
b11100 #
b11100 %
b11100 '
b11100 )
#600
1!
b100 (
b100 +
b10100 *
b100 :
b1001 9
b1 >
1=
b1 8
b11101 #
b11101 %
b11101 '
b11101 )
#620
0!
b10 (
b10 +
b10010 *
b10 :
b1 <
1;
b110 9
b10 >
0=
b10 8
b11110 #
b11110 %
b11110 '
b11110 )
#640
1!
b1 (
b1 +
b10001 *
b1 :
b101 9
b1 >
1=
b11 8
b11111 #
b11111 %
b11111 '
b11111 )
