Ass 1 7B/R11617302.v
module top(A, B, C, D, F);

input A, B, C, D;
output F;

// YOUR VERILOG CODE BELOW
assign F = B&D | A&B&~C | ~A&B&C | A&C&D | ~A&~B&~C&~D;

//juju on that beat ayy

endmodule

Ass 1 7B/R11617302_tb.v
`timescale 1ns / 1ns
`include "R11617302.v"

module R11617302_tb;

reg A, B, C, D;
wire F;

top uut(A, B, C, D, F);

initial begin

    $dumpfile("R11617302_tb.vcd");
    $dumpvars(0, R11617302_tb);

   // {A,B} = 4'b0000 for binary
   {A,B,C,D} = 4'd0; #20;
   {A,B,C,D} = 4'd1; #20;
   {A,B,C,D} = 4'd2; #20;
   {A,B,C,D} = 4'd3; #20;
   {A,B,C,D} = 4'd4; #20;
   {A,B,C,D} = 4'd5; #20;
   {A,B,C,D} = 4'd6; #20;
   {A,B,C,D} = 4'd7; #20;
   {A,B,C,D} = 4'd8; #20;
   {A,B,C,D} = 4'd9; #20;
   {A,B,C,D} = 4'd10; #20;
   {A,B,C,D} = 4'd11; #20;
   {A,B,C,D} = 4'd12; #20;
   {A,B,C,D} = 4'd13; #20;
   {A,B,C,D} = 4'd14; #20;
   {A,B,C,D} = 4'd15; #20;
   $display("Test is complete.");
end

endmodule
//iverilog -o greater_than_tb.vvp greater_than_tb.v
//vvp greater_than_tb.vvp
//gtkwave
//new tab, then open the .vcd file

//iverilog -o R11617302_tb.vvp R11617302_tb.v
//

Ass 1 7B/R11617302_tb.vcd
$date
	Mon Apr 06 18:27:43 2020
$end
$version
	Icarus Verilog
$end
$timescale
	1ns
$end
$scope module R11617302_tb $end
$var wire 1 ! F $end
$var reg 1 " A $end
$var reg 1 # B $end
$var reg 1 $ C $end
$var reg 1 % D $end
$scope module uut $end
$var wire 1 " A $end
$var wire 1 # B $end
$var wire 1 $ C $end
$var wire 1 % D $end
$var wire 1 ! F $end
$upscope $end
$upscope $end
$enddefinitions $end
#0
$dumpvars
0%
0$
0#
0"
1!
$end
#20
0!
1%
#40
0!
1$
0%
#60
1%
#80
0!
1#
0$
0%
#100
1!
1%
#120
1$
0%
#140
1%
#160
0!
1"
0#
0$
0%
#180
1%
#200
1$
0%
#220
1!
1%
#240
1!
1#
0$
0%
#260
1%
#280
0!
1$
0%
#300
1!
1%
